MANIFEST.in
README.rst
setup.py
drf_dark_theme/__init__.py
drf_dark_theme/renderers.py
drf_dark_theme/settings.py
drf_dark_theme.egg-info/PKG-INFO
drf_dark_theme.egg-info/SOURCES.txt
drf_dark_theme.egg-info/dependency_links.txt
drf_dark_theme.egg-info/not-zip-safe
drf_dark_theme.egg-info/requires.txt
drf_dark_theme.egg-info/top_level.txt
drf_dark_theme/static/.DS_Store
drf_dark_theme/static/drf_dark_theme/.DS_Store
drf_dark_theme/static/drf_dark_theme/css/moonshine.css
drf_dark_theme/static/drf_dark_theme/css/stellar.css
drf_dark_theme/static/drf_dark_theme/img/moonshine-palette.png
drf_dark_theme/static/drf_dark_theme/img/moonshine-ss.png
drf_dark_theme/static/drf_dark_theme/img/stellar-palette.png
drf_dark_theme/static/drf_dark_theme/img/stellar-ss.png
drf_dark_theme/templates/moonshine-api.html
drf_dark_theme/templates/stellar-api.html