Metadata-Version: 1.1
Name: drf-dark-theme
Version: 0.3
Summary: Dark Themes for Django Rest Framework
Home-page: https://github.com/aledista/drf-dark-theme
Author: Alessio Di Stasio
Author-email: aledista@gmail.com
License: BSD
Platform: UNKNOWN
Classifier: Development Status :: 4 - Beta
Classifier: Environment :: Web Environment
Classifier: Intended Audience :: Developers
Classifier: License :: OSI Approved :: BSD License
Classifier: Operating System :: OS Independent
Classifier: Programming Language :: Python
